imgvision/__init__.py
imgvision/__version__.py
imgvision/data/A_D75.npy
imgvision/data/CIExyz_deg10.npy
imgvision/data/CIExyz_deg2.npy
imgvision/data/__init__.py
imgvision/data/a.npy
imgvision/data/b.npy
imgvision/data/c.npy
imgvision/data/cie64.npy
imgvision/data/d50.npy
imgvision/data/d55.npy
imgvision/data/d65.npy
imgvision-0.1.7.3.dist-info/LICENSE
imgvision-0.1.7.3.dist-info/METADATA
imgvision-0.1.7.3.dist-info/WHEEL
imgvision-0.1.7.3.dist-info/top_level.txt
imgvision-0.1.7.3.dist-info/RECORD
