Metadata-Version: 2.1
Name: imgvision
Version: 0.1.7.3
Summary: A package for image vision
Home-page: https://blog.csdn.net/syuhen/category_11306284.html
Author: Xuheng Cao
Author-email: caoxuhengcn@gmail.com
License: UNKNOWN
Platform: UNKNOWN
Classifier: License :: OSI Approved :: MIT License
License-File: LICENSE
Requires-Dist: numpy
